humani_py/__init__.py
humani_py/delays.py
humani_py/movements.py
humani_py/scrolling.py
humani_py/stealth.py
humani_py/typing.py
humani_py/utils.py
humani_py-0.1.1.dist-info/LICENSE
humani_py-0.1.1.dist-info/METADATA
humani_py-0.1.1.dist-info/WHEEL
humani_py-0.1.1.dist-info/RECORD
