Metadata-Version: 2.1
Name: humani_py
Version: 0.1.1
Summary: A package to simulate human-like behavior in automation tasks.
License: MIT
Author: Shreenidhi H D
Author-email: shreenidhihaagalagodu@gmail.com
Requires-Python: >=3.7,<4.0
Classifier: License :: OSI Approved :: MIT License
Classifier: Programming Language :: Python :: 3
Classifier: Programming Language :: Python :: 3.7
Classifier: Programming Language :: Python :: 3.8
Classifier: Programming Language :: Python :: 3.9
Classifier: Programming Language :: Python :: 3.10
Classifier: Programming Language :: Python :: 3.11
Classifier: Programming Language :: Python :: 3.12
Requires-Dist: fake-useragent (>=0.1.11,<0.2.0)
Requires-Dist: pyautogui (>=0.9.53,<0.10.0)
Requires-Dist: selenium (>=4.0.0,<5.0.0) ; python_version >= "3.7"
Requires-Dist: undetected-chromedriver (>=3.0.0,<4.0.0)
